setup.cfg
setup.py
docuit/__init__.py
docuit/__main__.py
docuit/_version.py
docuit.egg-info/PKG-INFO
docuit.egg-info/SOURCES.txt
docuit.egg-info/dependency_links.txt
docuit.egg-info/entry_points.txt
docuit.egg-info/requires.txt
docuit.egg-info/top_level.txt