Metadata-Version: 1.1
Name: docuit
Version: 0.4
Summary: Docuit is a tool which makes sure your README stays up to date and simplifies getting the needed parts out of the README.
Home-page: https://github.com/TooAngel/docuit
Author: Tobias Wilken
Author-email: tooangel@tooangel.de
License: AGPL-3.0
Download-URL: https://pypi.python.org/pypi/docuit
Platform: Any
Classifier: Development Status :: 4 - Beta
Classifier: Environment :: Console
Classifier: Intended Audience :: End Users/Desktop
Classifier: Intended Audience :: Developers
Classifier: Intended Audience :: System Administrators
Classifier: License :: OSI Approved :: GNU Affero General Public License v3 or later (AGPLv3+)
Classifier: Operating System :: MacOS :: MacOS X
Classifier: Operating System :: Microsoft :: Windows
Classifier: Operating System :: POSIX
Classifier: Programming Language :: Python
Classifier: Topic :: Documentation
Classifier: Topic :: Software Development
Classifier: Topic :: Software Development :: Build Tools
Classifier: Topic :: Software Development :: Documentation
Classifier: Topic :: Software Development :: Testing
Classifier: Topic :: System :: Boot
Classifier: Topic :: System :: Systems Administration
Classifier: Topic :: Text Processing :: Markup
Classifier: Topic :: Utilities
